pyladder/__init__.py
pyladder/pyladder.py
pyladder-0.0.8.dist-info/LICENSE
pyladder-0.0.8.dist-info/METADATA
pyladder-0.0.8.dist-info/WHEEL
pyladder-0.0.8.dist-info/top_level.txt
pyladder-0.0.8.dist-info/RECORD
