Metadata-Version: 2.1
Name: pyladder
Version: 0.0.8
Summary: A python package for planarity testing and rendering of ladder type graphs
Home-page: https://github.com/haraldujc/pyladder
Author: Harald Ujc
Author-email: harald.ujc@screenpopsoftware.com
Maintainer: Harald ujc
Maintainer-email: harald.ujc@screenpopsoftware.com
License: BSD License
Platform: UNKNOWN
Classifier: Intended Audience :: Developers
Classifier: Intended Audience :: Science/Research
Classifier: License :: OSI Approved :: BSD License
Classifier: Operating System :: OS Independent
Classifier: Programming Language :: Python :: 3.7
Classifier: Topic :: Software Development :: Libraries :: Python Modules
Classifier: Topic :: Scientific/Engineering :: Mathematics
Classifier: Topic :: Scientific/Engineering :: Physics
Requires-Python: >=3.6
